Workbook

Sheet Financials
A1: APPLE INC. - FINANCIAL ANALYSIS
A3: Metric | B3: FY2024 | C3: FY2025 | D3: FY2026 YTD | E3: Notes
A4: Revenue | B4: 391035 | C4: 416161 | D4: 328032
A5: Net Income | B5: 93736 | C5: 112010 | D5: 101464
A6: Gross Margin | B6: 0.4621 | C6: 0.4691 | D6: 0.4906
A7: Operating Margin | B7: 0.3151 | C7: 0.3245 | D7: N/A | E7: Operating income for the comparable FY2026 YTD period is not included in the current model; operating margin therefore cannot be calculated reliably.
A8: Cash & Cash Equivalents | B8: 29943 | C8: 35934 | D8: 35237
A9: Total Debt | B9: 106629 | C9: 98657 | D9: 96965
A10: Services Revenue | B10: 96169 | C10: 109158 | D10: 91728
A11: Operating Cash Flow | B11: 118254 | C11: 111482 | D11: 116996
A12: Capital Expenditures | B12: 9447 | C12: 12715 | D12: 6799
A13: Free Cash Flow | B13: =B11-B12 -> 108807 | C13: =C11-C12 -> 98767 | D13: =D11-D12 -> 110197

Sheet Calculations
A1: APPLE INC. - FINANCIAL CALCULATIONS
A3: Metric | B3: FY2024 | C3: FY2025 | D3: FY2026 YTD | E3: Change (24-25) | F3: Interpretation
A4: Revenue Growth | B4: N/A | C4: =(Financials!C4/Financials!B4)-1 -> 0.064255118 | D4: 0.1078 | E4: =C4 -> 0.064255118 | F4: Growth accelerated, with FY2026 YTD revenue increasing faster than FY2025.
A5: Net Income Growth | B5: N/A | C5: =(Financials!C5/Financials!B5)-1 -> 0.19495178 | D5: 0.2844 | E5: =C5 -> 0.19495178 | F5: Net income growth accelerated significantly, indicating stronger earnings growth than revenue.
A6: Gross Margin | B6: =Financials!B6 -> 0.4621 | C6: =Financials!C6 -> 0.4691 | D6: 0.4906 | E6: =C6-B6 -> 0.007 | F6: Gross margin improved, suggesting stronger profitability on each dollar of revenue.
A7: Operating Margin | B7: =Financials!B7 -> 0.3151 | C7: =Financials!C7 -> 0.3245 | D7: N/A | E7: =C7-B7 -> 0.0094 | F7: Operating margin improved from FY2024 to FY2025, indicating stronger operating profitability.
A8: Services Revenue Growth | B8: N/A | C8: =(Financials!C10/Financials!B10)-1 -> 0.13506431 | D8: 0.2884 | E8: =C8 -> 0.13506431 | F8: Services growth accelerated substantially, highlighting Services as an important growth driver.
A9: Free Cash Flow | B9: =Financials!B13 -> 108807 | C9: =Financials!C13 -> 98767 | D9: 110197 | E9: =C9-B9 -> -10040 | F9: FY2025 free cash flow declined from FY2024, but FY2026 YTD already exceeds FY2025 full-year FCF.
A10: Free Cash Flow Margin | B10: =B9/Financials!B4 -> 0.27825386 | C10: =C9/Financials!C4 -> 0.23732882 | D10: 0.3359 | E10: =C10-B10 -> -0.040925042 | F10: FCF margin declined in FY2025 but increased sharply in FY2026 YTD, indicating stronger cash generation relative to revenue.

Sheet Valuation
A1: APPLE INC. - VALUATION & MARKET DATA
A3: Metric | B3: Value | C3: Date | D3: What It Suggests
A4: Market Capitalization | B4: 4411000 | C4: 46246 | D4: Apple's enormous market capitalization reflects its scale, brand strength, ecosystem, and investor expectations for continued long-term growth.
A5: Enterprise Value | B5: =B4+Financials!C9-Financials!C8 -> 4473723 | C5: 46246 | D5: Enterprise value accounts for both equity value and net debt, providing a broader measure of Apple's overall business value.
A6: P/E Ratio | B6: 34 | C6: 46246 | D6: Apple's relatively high P/E indicates that investors are paying a premium for its earnings, reflecting expectations for continued profitability and growth.
A7: Revenue Growth | B7: =Calculations!C4 -> 0.064255118 | C7: 46246 | D7: Revenue growth was positive but moderate, highlighting the importance of Services, new products, and strategic investments to sustain future growth.
A8: Free Cash Flow Yield | B8: N/A | C8: 46246 | D8: TTM free cash flow is required for a comparable FCF yield; current model contains YTD FCF only.
A9: Other Relevant Metric | B9: P/B Ratio | C9: 46246 | D9: Price-to-book provides an additional valuation perspective, although it is less informative for Apple than earnings and cash-flow measures because of its large share repurchase program.

Sheet M&A Analysis
A1: APPLE INC. - M&A TARGET ANALYSIS
A3: Target/Capability | B3: Strategic Fit | C3: Capability Gap | D3: Synergy Potential | E3: Integration Risk | F3: Acquistion Cost Attractiveness | G3: Overall Rating | H3: Score
A4: AI / Machine Learning | B4: 9 | C4: 9 | D4: 8 | E4: 6 | F4: 5 | G4: =IF(H4>=8.5,"Very High",IF(H4>=7,"High",IF(H4>=5,"Moderate",IF(H4>=3,"Low","Very Low")))) -> High | H4: =AVERAGE(B4:F4) -> 7.4
A5: Health Technology | B5: 8 | C5: 8 | D5: 8 | E5: 6 | F5: 6 | G5: =IF(H5>=8.5,"Very High",IF(H5>=7,"High",IF(H5>=5,"Moderate",IF(H5>=3,"Low","Very Low")))) -> High | H5: =AVERAGE(B5:F5) -> 7.2
A6: Semiconductor / Chip Technology | B6: 9 | C6: 7 | D6: 9 | E6: 7 | F6: 5 | G6: =IF(H6>=8.5,"Very High",IF(H6>=7,"High",IF(H6>=5,"Moderate",IF(H6>=3,"Low","Very Low")))) -> High | H6: =AVERAGE(B6:F6) -> 7.4
A7: Robotics / Automation | B7: 7 | C7: 8 | D7: 8 | E7: 5 | F7: 5 | G7: =IF(H7>=8.5,"Very High",IF(H7>=7,"High",IF(H7>=5,"Moderate",IF(H7>=3,"Low","Very Low")))) -> Moderate | H7: =AVERAGE(B7:F7) -> 6.6
A8: Content / Media Technology | B8: 6 | C8: 5 | D8: 6 | E8: 7 | F8: 7 | G8: =IF(H8>=8.5,"Very High",IF(H8>=7,"High",IF(H8>=5,"Moderate",IF(H8>=3,"Low","Very Low")))) -> Moderate | H8: =AVERAGE(B8:F8) -> 6.2
A10: RATING SCALE
A11: Very High | B11: 8.5-10.0
A12: High | B12: 7.0-8.4
A13: Moderate | B13: 5.0-6.9
A14: Low | B14: 3.0-4.9
A15: Very Low | B15: 0-2.9
A17: Note
A18: Scores are preliminary analyst assessments based on strategic fit, capability gaps, potential synergies, integration considerations, and acquisition-cost attractiveness. They are not estimates of Apple's actual acquisition plans or transaction valuations.
A20: PRELIMINARY M&A CONCLUSION
A21: Highest-Ranked Capability | B21: =INDEX(A4:A8,MATCH(MAX(H4:H8),H4:H8,0)) -> AI / Machine Learning
A22: Highest Score | B22: =MAX(H4:H8) -> 7.4
A23: Overall Recommendation | B23: Investigate selectively
A24: Reasoning | B24: AI and semiconductor capabilities currently show the strongest strategic attractiveness in this preliminary screen. Apple should investigate potential targets selectively rather than pursue an acquisition solely because a capability is strategically attractive. Any transaction should be supported by a strong strategic fit, defensible technology or talent, manageable integration risk, and an acceptable acquisition cost.
A27: BUILD VS. BUY VS. PARTNER
A28: Capability | B28: Build | C28: Buy | D28: Partner | E28: Preferred Approach | F28: Reasoning
A29: AI / Maching Learning | B29: High | C29: High | D29: High | E29: Build + Partner | F29: Apple can develop proprietary AI capabilities internally while using partnerships to accelerate access to specialized models, infrastructure, and talent. An acquisition could provide speed and talent but would carry greater integration and cost risks.
A30: Health Technology | B30: High | C30: Moderate | D30: High | E30: Build + Partner | F30: Apple's existing ecosystem provides a strong foundation for health features, while partnerships can add specialized capabilities without requiring Apple to acquire an entire healthcare company.
A31: Semiconductor / Chip Technology | B31: High | C31: High | D31: High | E31: Build + Buy | F31: Apple already has significant chip-design capabilities, making internal development attractive. Selective acquisitions could accelerate access to specialized semiconductor technology or engineering talent.
A32: Robotics / Automation | B32: Moderate | C32: High | D32: High | E32: Partner + Buy | F32: Robotics could require specialized capabilities that Apple does not currently possess at the same scale. Partnerships could reduce uncertainty while selective acquisitions could accelerate access to specialized technology and talent.
A33: Content / Media Technology | B33: High | C33: Moderate | D33: High | E33: Build + Partner | F33: Apple can continue developing its existing content ecosystem while partnering with creators and media companies. Large acquisitions may create unnecessary integration complexity.
A35: M&A SCREENING CONCLUSION
A36: Preferred Strategy | B36: Selective Build + Buy + Partner
A37: Primary Priority | B37: AI / Machine Learning
A38: Secondary Priority | B38: Semiconductor / Chip Technology
A39: Key Principle | B39: Acquire capabilities when speed, talent, or intellectual property justify the cost of buying rather than building internally.
A40: Conclusion | B40: Apple should not pursue acquisitions simply to expand its portfolio. Corporate development should focus on targeted transactions that provide capabilities Apple cannot efficiently develop internally, while partnerships and internal investment remain preferable where Apple already has strong capabilities.

Sheet Charts
A1: APPLE INC. - KEY ANALYSIS CHARTS

Sheet Sources
A1: APPLE INC. - SOURCES
A3: Source | B3: Report/Article Title | C3: Date | D3: Date Accessed | E3: Used For
A4: Apple Inc. | B4: Apple Reports Third Quarter Results | C4: 46233 | D4: 46249 | E4: FY2026 YTD
A5: Apple Inc. | B5: FY2025 Q3 Consolidated Financial Statements | C5: July, 2025 | D5: 46249 | E5: Comparable FY2025 YTD
A6: Apple Inc. | B6: Apple Annual Report / Form 10-K | C6: 2025 | D6: 46249 | E6: FY2024 and FY2025 annual
A7: Apple Inc. | B7: Apple Investor Relations | C7: Ongoing | D7: 46249 | E7: Investor information and financial reporting reference
A8: Apple Inc. | B8: Apple Intelligence Brings Powerful AI Capabilities into everyday experiences | C8: 46181 | D8: 46249 | E8: AI Strategy, Apple Intelligence, Siri, and AI architecture
A9: Apple Inc. | B9: WWDC26: Apple Unveils Next Generation of Apple Intelligence, Siri Ai, and more | C9: 46181 | D9: 46249 | E9: Strategic AI opportunity and product ecosystem analysis
